chemevolve/APSfunctions.py
chemevolve/BinaryPolymer.py
chemevolve/CoreClasses.py
chemevolve/InitializeFunctions.py
chemevolve/OutputFunctions.py
chemevolve/Plotting.py
chemevolve/PropensityFunctions.py
chemevolve/ReactionFunctions.py
chemevolve/__init__.py
chemevolve/clibs/Linux-SSA.so
chemevolve/clibs/OSX-SSA.so
chemevolve/clibs/SSA.c
chemevolve/clibs/Win-SSA.so
chemevolve-0.0.8.dist-info/DESCRIPTION.rst
chemevolve-0.0.8.dist-info/METADATA
chemevolve-0.0.8.dist-info/RECORD
chemevolve-0.0.8.dist-info/WHEEL
chemevolve-0.0.8.dist-info/metadata.json
chemevolve-0.0.8.dist-info/top_level.txt
