Metadata-Version: 2.0
Name: chemevolve
Version: 0.0.8
Summary: Tools for Simulating Chemical Evoltion
Home-page: https://github.com/elife-asu/chemevolve
Author: Cole Mathis
Author-email: cole.mathis@asu.edu
License: MIT License
Requires-Dist: matplotlib
Requires-Dist: numpy
Requires-Dist: seaborn
